NiukeKuaixiaoXingyeMingqiBiMianshiXiaozhaoQiuzhiGonglve20212022/README.md
NiukeKuaixiaoXingyeMingqiBiMianshiXiaozhaoQiuzhiGonglve20212022/__init__.py
NiukeKuaixiaoXingyeMingqiBiMianshiXiaozhaoQiuzhiGonglve20212022/__main__.py
NiukeKuaixiaoXingyeMingqiBiMianshiXiaozhaoQiuzhiGonglve20212022/file.epub
NiukeKuaixiaoXingyeMingqiBiMianshiXiaozhaoQiuzhiGonglve20212022/index.html
NiukeKuaixiaoXingyeMingqiBiMianshiXiaozhaoQiuzhiGonglve20212022/css/__init__.py
NiukeKuaixiaoXingyeMingqiBiMianshiXiaozhaoQiuzhiGonglve20212022/css/annotations.css
NiukeKuaixiaoXingyeMingqiBiMianshiXiaozhaoQiuzhiGonglve20212022/css/main.css
NiukeKuaixiaoXingyeMingqiBiMianshiXiaozhaoQiuzhiGonglve20212022/css/normalize.css
NiukeKuaixiaoXingyeMingqiBiMianshiXiaozhaoQiuzhiGonglve20212022/css/popup.css
NiukeKuaixiaoXingyeMingqiBiMianshiXiaozhaoQiuzhiGonglve20212022/font/__init__.py
NiukeKuaixiaoXingyeMingqiBiMianshiXiaozhaoQiuzhiGonglve20212022/font/fontello.eot
NiukeKuaixiaoXingyeMingqiBiMianshiXiaozhaoQiuzhiGonglve20212022/font/fontello.svg
NiukeKuaixiaoXingyeMingqiBiMianshiXiaozhaoQiuzhiGonglve20212022/font/fontello.ttf
NiukeKuaixiaoXingyeMingqiBiMianshiXiaozhaoQiuzhiGonglve20212022/font/fontello.woff
NiukeKuaixiaoXingyeMingqiBiMianshiXiaozhaoQiuzhiGonglve20212022/img/__init__.py
NiukeKuaixiaoXingyeMingqiBiMianshiXiaozhaoQiuzhiGonglve20212022/img/annotator-glyph-sprite.png
NiukeKuaixiaoXingyeMingqiBiMianshiXiaozhaoQiuzhiGonglve20212022/img/annotator-icon-sprite.png
NiukeKuaixiaoXingyeMingqiBiMianshiXiaozhaoQiuzhiGonglve20212022/img/apple-touch-icon.png
NiukeKuaixiaoXingyeMingqiBiMianshiXiaozhaoQiuzhiGonglve20212022/img/cancelfullscreen.png
NiukeKuaixiaoXingyeMingqiBiMianshiXiaozhaoQiuzhiGonglve20212022/img/close.png
NiukeKuaixiaoXingyeMingqiBiMianshiXiaozhaoQiuzhiGonglve20212022/img/fullscreen.png
NiukeKuaixiaoXingyeMingqiBiMianshiXiaozhaoQiuzhiGonglve20212022/img/loader.gif
NiukeKuaixiaoXingyeMingqiBiMianshiXiaozhaoQiuzhiGonglve20212022/img/menu-icon.png
niuke_kuaixiao_xingye_mingqi_bi_mianshi_xiaozhao_qiuzhi_gonglve_2021_2022-2024.3.6.0.dist-info/METADATA
niuke_kuaixiao_xingye_mingqi_bi_mianshi_xiaozhao_qiuzhi_gonglve_2021_2022-2024.3.6.0.dist-info/WHEEL
niuke_kuaixiao_xingye_mingqi_bi_mianshi_xiaozhao_qiuzhi_gonglve_2021_2022-2024.3.6.0.dist-info/entry_points.txt
niuke_kuaixiao_xingye_mingqi_bi_mianshi_xiaozhao_qiuzhi_gonglve_2021_2022-2024.3.6.0.dist-info/top_level.txt
niuke_kuaixiao_xingye_mingqi_bi_mianshi_xiaozhao_qiuzhi_gonglve_2021_2022-2024.3.6.0.dist-info/RECORD
